flore/__init__.py
flore/__version__.py
flore/facede.py
flore/flore.py
flore/libraries/base.py
flore/libraries/pg.py
flore/libraries/yaml.py
flore/normalize/__init__.py
flore/normalize/colon.py
flore/normalize/required.py
flore/table.py
flore/utils.py
flore-0.0.3.dist-info/LICENSE
flore-0.0.3.dist-info/METADATA
flore-0.0.3.dist-info/WHEEL
flore-0.0.3.dist-info/entry_points.txt
flore-0.0.3.dist-info/RECORD
