Metadata-Version: 2.1
Name: flore
Version: 0.0.3
Summary: A great option for creating SQL tables in yaml format.
Home-page: https://github.com/marcuxyz/flore
License: MIT
Keywords: python,flore-sql,yaml to sql,yamlsql,transpile sql,sql tests,migrations,migrate,orm
Author: Marcus Pereira
Author-email: hi@marcuspereira.dev
Requires-Python: >=3.8,<4.0
Classifier: License :: OSI Approved :: MIT License
Classifier: Programming Language :: Python :: 3
Classifier: Programming Language :: Python :: 3.8
Classifier: Programming Language :: Python :: 3.9
Classifier: Programming Language :: Python :: 3.10
Classifier: Programming Language :: Python :: 3.11
Requires-Dist: psycopg2-binary (>=2.9.7,<3.0.0)
Requires-Dist: pyyaml (>=6.0.1,<7.0.0)
Requires-Dist: typer[all] (>=0.9.0,<0.10.0)
Project-URL: Repository, https://github.com/marcuxyz/flore
